{
  "light": {
    "text": {
      "main": {
        "value": "#2f2f2f",
        "type": "color",
        "description": "Основной текст для светлой темы"
      },
      "secondary": {
        "value": "#9f9f9f",
        "type": "color",
        "description": "Дополнительный текст для светлой темы"
      },
      "disabled": {
        "value": "#d9d9d9",
        "type": "color",
        "description": "Дизейблд текст для светлой темы"
      },
      "inverted": {
        "value": "#f8f8f8",
        "type": "color"
      }
    },
    "components": {
      "hover": {
        "value": "#ececec",
        "type": "color"
      }
    },
    "fill": {
      "bg": {
        "value": "#ffffff",
        "type": "color",
        "description": "Задний фон для светлой темы"
      },
      "controls": {
        "value": "#f8f8f8",
        "type": "color"
      },
      "outline": {
        "value": "#000000",
        "type": "color"
      }
    },
    "semantics": {
      "green": {
        "main": {
          "value": "#009400",
          "type": "color"
        },
        "secondary": {
          "value": "#d9ffd4",
          "type": "color"
        },
        "disabled": {
          "value": "#f0ffee",
          "type": "color"
        },
        "hover": {
          "value": "#b4ffab",
          "type": "color"
        },
        "active": {
          "value": "#6dff5f",
          "type": "color"
        }
      },
      "red": {
        "main": {
          "value": "#ff1a00",
          "type": "color"
        },
        "secondary": {
          "value": "#ffe1d2",
          "type": "color"
        },
        "disabled": {
          "value": "#fff2ec",
          "type": "color"
        },
        "hover": {
          "value": "#ffbfa4",
          "type": "color"
        },
        "active": {
          "value": "#ff8f6a",
          "type": "color"
        }
      },
      "yellow": {
        "main": {
          "value": "#f8eb00",
          "type": "color"
        }
      },
      "black": {
        "main": {
          "value": "#000000",
          "type": "color"
        }
      },
      "gray": {
        "default": {
          "value": "#f8f8f8",
          "type": "color"
        },
        "hover": {
          "value": "#ececec",
          "type": "color"
        },
        "active": {
          "value": "#c9c9c9",
          "type": "color"
        }
      },
      "blue": {
        "50": {
          "value": "#f0f5fe",
          "type": "color"
        },
        "100": {
          "value": "#dceafd",
          "type": "color"
        },
        "200": {
          "value": "#c1dbfa",
          "type": "color"
        },
        "300": {
          "value": "#96c3f5",
          "type": "color"
        },
        "400": {
          "value": "#599dee",
          "type": "color"
        },
        "500": {
          "value": "#3e81e9",
          "type": "color"
        },
        "600": {
          "value": "#2c64dd",
          "type": "color"
        },
        "700": {
          "value": "#2651cb",
          "type": "color"
        },
        "800": {
          "value": "#2844a6",
          "type": "color"
        },
        "900": {
          "value": "#253c83",
          "type": "color"
        },
        "950": {
          "value": "#1c2651",
          "type": "color"
        },
        "1000": {
          "value": "#0d122d",
          "type": "color"
        }
      }
    }
  },
  "dark": {
    "text": {
      "main": {
        "value": "#ececec",
        "type": "color"
      },
      "inverted": {
        "value": "#2f2f2f",
        "type": "color"
      },
      "disabled": {
        "value": "#5d5d5d",
        "type": "color"
      },
      "secondary": {
        "value": "#3d4049",
        "type": "color"
      }
    },
    "semantics": {
      "red": {
        "main": {
          "value": "#ff4433",
          "type": "color"
        },
        "active": {
          "value": "#ff6b5c",
          "type": "color"
        },
        "hover": {
          "value": "#780a00",
          "type": "color"
        },
        "disabled": {
          "value": "#2e0f08",
          "type": "color"
        },
        "secondary": {
          "value": "#4a1508",
          "type": "color"
        }
      },
      "blue": {
        "50": {
          "value": "#161b25",
          "type": "color"
        },
        "100": {
          "value": "#172238",
          "type": "color"
        },
        "200": {
          "value": "#172848",
          "type": "color"
        },
        "300": {
          "value": "#173159",
          "type": "color"
        },
        "400": {
          "value": "#15386b",
          "type": "color"
        },
        "500": {
          "value": "#143e7c",
          "type": "color"
        },
        "600": {
          "value": "#14448f",
          "type": "color"
        },
        "700": {
          "value": "#134aa0",
          "type": "color"
        },
        "800": {
          "value": "#1451b1",
          "type": "color"
        },
        "900": {
          "value": "#0e58c2",
          "type": "color"
        },
        "950": {
          "value": "#0c5ed3",
          "type": "color"
        },
        "1000": {
          "value": "#0a64e4",
          "type": "color"
        }
      },
      "green": {
        "active": {
          "value": "#00e660",
          "type": "color"
        },
        "main": {
          "value": "#00c94d",
          "type": "color"
        },
        "disabled": {
          "value": "#0a2618",
          "type": "color"
        },
        "hover": {
          "value": "#00702c",
          "type": "color"
        },
        "secondary": {
          "value": "#003d1a",
          "type": "color"
        }
      },
      "gray": {
        "default": {
          "value": "#212121",
          "type": "color"
        }
      }
    },
    "fill": {
      "outline": {
        "value": "#ffffff",
        "type": "color"
      },
      "bg": {
        "value": "#1c1c1c",
        "type": "color"
      },
      "controls": {
        "value": "#1f1f1f",
        "type": "color"
      }
    },
    "components": {
      "hover": {
        "value": "#5d5d5d",
        "type": "color"
      }
    }
  }
}